makefile2dot/__init__.py
makefile2dot/test_makefile2dot.py
makefile2dot-1.0.2.data/scripts/makefile2dot
makefile2dot-1.0.2.dist-info/METADATA
makefile2dot-1.0.2.dist-info/WHEEL
makefile2dot-1.0.2.dist-info/top_level.txt
makefile2dot-1.0.2.dist-info/RECORD
