Metadata-Version: 2.1
Name: makefile2dot
Version: 1.0.2
Summary: Create a graphviz graph of a Makefile.
Home-page: https://github.com/chadsgilbert/makefile2dot
Author: Chad Gilbert
Author-email: chad.s.gilbert@gmail.com
License: UNKNOWN
Platform: UNKNOWN
Classifier: Programming Language :: Python :: 3.7
Classifier: Operating System :: POSIX
Requires-Dist: graphviz
